flamel/__init__.py
flamel/base.py
flamel/column.py
flamel/dialect.py
flamel/query.py
flamel_orm-0.0.5.dist-info/LICENSE
flamel_orm-0.0.5.dist-info/METADATA
flamel_orm-0.0.5.dist-info/WHEEL
flamel_orm-0.0.5.dist-info/top_level.txt
flamel_orm-0.0.5.dist-info/RECORD
