Metadata-Version: 2.1
Name: flamel-orm
Version: 0.0.5
Summary: A simple declarative ORM for SQLite
Author-email: fernando24164 <fernando24164@gmail.com>
License: MIT
Project-URL: Repository, https://github.com/fernando24164/flamel
Keywords: ORM,simple
Classifier: Programming Language :: Python :: 3.8
Classifier: Development Status :: 3 - Alpha
Requires-Python: >=3.8
License-File: LICENSE
